src/__init__.py
src/topsis.py
Topsis_Amrita_102017017-1.0.0.dist-info/LICENSE
Topsis_Amrita_102017017-1.0.0.dist-info/METADATA
Topsis_Amrita_102017017-1.0.0.dist-info/WHEEL
Topsis_Amrita_102017017-1.0.0.dist-info/entry_points.txt
Topsis_Amrita_102017017-1.0.0.dist-info/top_level.txt
Topsis_Amrita_102017017-1.0.0.dist-info/RECORD
