Metadata-Version: 2.1
Name: Topsis-Amrita-102017017
Version: 1.0.0
Summary: A command line tool to perform TOPSIS, a multi-criteria decision making technique
Author: Amrita Bhatia
Author-email: <nonie.bhatia@gmail.com>
Keywords: python,TOPSIS,MCDM,MCDA,statistics,prescriptive analytics,cli
Classifier: Intended Audience :: Science/Research
Classifier: Topic :: Scientific/Engineering :: Information Analysis
Classifier: Programming Language :: Python :: 3
Classifier: License :: OSI Approved :: MIT License
Classifier: Operating System :: OS Independent
Requires-Python: >=3.5
License-File: LICENSE
